zope/copypastemove/__init__.py
zope/copypastemove/configure.zcml
zope/copypastemove/interfaces.py
zope/copypastemove/tests/__init__.py
zope/copypastemove/tests/test_clipboard.py
zope/copypastemove/tests/test_configure.py
zope/copypastemove/tests/test_metadata.py
zope/copypastemove/tests/test_objectcopier.py
zope/copypastemove/tests/test_objectmover.py
zope/copypastemove/tests/test_rename.py
zope_copypastemove-6.0.dist-info/licenses/LICENSE.txt
zope_copypastemove-6.0.dist-info/METADATA
zope_copypastemove-6.0.dist-info/WHEEL
zope_copypastemove-6.0.dist-info/top_level.txt
zope_copypastemove-6.0.dist-info/RECORD
