Metadata-Version: 2.4
Name: zope.copypastemove
Version: 6.0
Summary: Copy, Paste and Move support for content components.
Home-page: http://github.com/zopefoundation/zope.copypastemove
Author: Zope Foundation and Contributors
Author-email: zope-dev@zope.dev
License: ZPL-2.1
Classifier: Environment :: Web Environment
Classifier: Intended Audience :: Developers
Classifier: License :: OSI Approved :: Zope Public License
Classifier: Programming Language :: Python
Classifier: Programming Language :: Python :: 3
Classifier: Programming Language :: Python :: 3.9
Classifier: Programming Language :: Python :: 3.10
Classifier: Programming Language :: Python :: 3.11
Classifier: Programming Language :: Python :: 3.12
Classifier: Programming Language :: Python :: 3.13
Classifier: Programming Language :: Python :: Implementation :: CPython
Classifier: Programming Language :: Python :: Implementation :: PyPy
Classifier: Natural Language :: English
Classifier: Operating System :: OS Independent
Classifier: Topic :: Internet :: WWW/HTTP
Classifier: Framework :: Zope :: 3
Requires-Python: >=3.9
License-File: LICENSE.txt
Requires-Dist: setuptools
Requires-Dist: zope.annotation
Requires-Dist: zope.component
Requires-Dist: zope.container
Requires-Dist: zope.copy
Requires-Dist: zope.event
Requires-Dist: zope.exceptions
Requires-Dist: zope.interface
Requires-Dist: zope.lifecycleevent
Requires-Dist: zope.location
Provides-Extra: test
Requires-Dist: zope.component[zcml]; extra == "test"
Requires-Dist: zope.configuration; extra == "test"
Requires-Dist: zope.security[zcml]; extra == "test"
Requires-Dist: zope.dublincore>=3.8; extra == "test"
Requires-Dist: zope.principalannotation; extra == "test"
Requires-Dist: zope.testing; extra == "test"
Requires-Dist: zope.testrunner>=6.4; extra == "test"
Requires-Dist: zope.traversing; extra == "test"
Provides-Extra: zcml
Requires-Dist: zope.component[zcml]; extra == "zcml"
Requires-Dist: zope.configuration; extra == "zcml"
Requires-Dist: zope.security[zcml]; extra == "zcml"
Dynamic: author
Dynamic: author-email
Dynamic: classifier
Dynamic: description
Dynamic: home-page
Dynamic: license
Dynamic: license-file
Dynamic: provides-extra
Dynamic: requires-dist
Dynamic: requires-python
Dynamic: summary
